README.md
setup.py
netcash/__init__.py
netcash/client.py
netcash/payloads.py
python_netcash.egg-info/PKG-INFO
python_netcash.egg-info/SOURCES.txt
python_netcash.egg-info/dependency_links.txt
python_netcash.egg-info/requires.txt
python_netcash.egg-info/top_level.txt