Metadata-Version: 2.1
Name: python-netcash
Version: 0.0.1
Summary: UNKNOWN
Home-page: https://gitlab.com/schoolorchestration/libs/python-netcash
Author: Christo Crampton
Author-email: info@38.co.za
License: UNKNOWN
Platform: UNKNOWN
Classifier: Programming Language :: Python :: 3
Classifier: Operating System :: OS Independent
